{
  "project_info": {
    "project_number": "457148042769",
    "firebase_url": "https://guidee-f0453.firebaseio.com",
    "project_id": "guidee-f0453",
    "storage_bucket": "guidee-f0453.appspot.com"
  },
  "client": [
    {
      "client_info": {
        "mobilesdk_app_id": "1:457148042769:android:6500eb2f2ed803b7",
        "android_client_info": {
          "package_name": "zollie.travelblogger.guidee"
        }
      },
      "oauth_client": [
        {
          "client_id": "457148042769-utb8iall6pd9tr2fml56spu10hama0c0.apps.googleusercontent.com",
          "client_type": 1,
          "android_info": {
            "package_name": "zollie.travelblogger.guidee",
            "certificate_hash": "694beeeb7971b9c648d5cf2f31eab6b67ac9ef91"
          }
        },
        {
          "client_id": "457148042769-olsj1qqjut0hrbqrl48liki1uch4oqi5.apps.googleusercontent.com",
          "client_type": 3
        }
      ],
      "api_key": [
        {
          "current_key": "AIzaSyAKCtK1w54HxQkXB-X3uBORII-x_xpNc9k"
        }
      ],
      "services": {
        "analytics_service": {
          "status": 1
        },
        "appinvite_service": {
          "status": 2,
          "other_platform_oauth_client": [
            {
              "client_id": "457148042769-5nie2d4nbj2o7le50g94or3f2ee4prdb.apps.googleusercontent.com",
              "client_type": 2,
              "ios_info": {
                "bundle_id": "Zsombor.Fuszenecker.VoyageApp"
              }
            },
            {
              "client_id": "457148042769-olsj1qqjut0hrbqrl48liki1uch4oqi5.apps.googleusercontent.com",
              "client_type": 3
            }
          ]
        },
        "ads_service": {
          "status": 2
        }
      }
    }
  ],
  "configuration_version": "1"
}